observer_machine/__init__.py
observer_machine-0.0.2.dist-info/LICENSE
observer_machine-0.0.2.dist-info/METADATA
observer_machine-0.0.2.dist-info/WHEEL
observer_machine-0.0.2.dist-info/top_level.txt
observer_machine-0.0.2.dist-info/RECORD
